{
    "resource_group": "<RESOURCE_GROUP_NAME>",
    "subscription_id": "<SUBSCRIPTION_ID>",
    "digital_twins_name": "<DIGITAL_TWINS_RESOURCE_NAME>",
    "thumbprint_of_cert_in_der_format": "<THUMBPRINT_OF_CERT_IN_DER_FORMAT>",
    "storage_account_name": "<STORAGE_ACCOUNT_NAME>",
    "function_app_name": "<FUNCTION_APP_NAME>",
    "key_vault_name": "<KEYVAULT_NAME>",
    "event_grid_topic": "<EVENT_GRID_TOPIC>",
    "event_grid_subscription_name": "<EVENT_GRID_SUBSCRIPTION>",
    "event_grid_namespace": "<EVENT_GRID_NAMESPACE>",
    "mqtt_client_authentication_name": "<MQTT_CLIENT_AUTHENTICATION_NAME>"
}